tests/__init__.py
tests/pigpio_mocks.py
tests/test_alarms.py
tests/test_controller.py
tests/test_coordinator.py
tests/test_gui.py
tests/test_io_devices.py
tests/test_io_hal.py
tests/test_io_pins.py
tests/test_io_sensors.py
tests/test_io_valves.py
tests/test_logging.py
vent/__init__.py
vent/main.py
vent/alarm/__init__.py
vent/alarm/alarm.py
vent/alarm/alarm_manager.py
vent/alarm/condition.py
vent/alarm/rule.py
vent/common/__init__.py
vent/common/fashion.py
vent/common/logging.py
vent/common/message.py
vent/common/prefs.py
vent/common/values.py
vent/controller/__init__.py
vent/controller/control_module.py
vent/coordinator/__init__.py
vent/coordinator/coordinator.py
vent/coordinator/process_manager.py
vent/coordinator/rpc.py
vent/gui/__init__.py
vent/gui/alarm_manager.py
vent/gui/main.py
vent/gui/styles.py
vent/gui/widgets/__init__.py
vent/gui/widgets/components.py
vent/gui/widgets/control.py
vent/gui/widgets/monitor.py
vent/gui/widgets/plot.py
vent/gui/widgets/status_bar.py
vent/io/__init__.py
vent/io/hal.py
vent/io/devices/__init__.py
vent/io/devices/base.py
vent/io/devices/pins.py
vent/io/devices/sensors.py
vent/io/devices/valves.py
ventilator-0.0.2.dist-info/LICENSE
ventilator-0.0.2.dist-info/METADATA
ventilator-0.0.2.dist-info/WHEEL
ventilator-0.0.2.dist-info/top_level.txt
ventilator-0.0.2.dist-info/RECORD
