Metadata-Version: 2.1
Name: ventilator
Version: 0.0.2
Summary: some description of how we made a ventilator
Home-page: https://ventilator.readthedocs.io
Author: vent team
Author-email: vent@vents.com
License: UNKNOWN
Keywords: vents ventilators etc
Platform: UNKNOWN
Requires-Python: ==3.7.*
Requires-Dist: numpy
Requires-Dist: PySide2 (==5.11.*)
Requires-Dist: pyqtgraph (>=0.11.0rc0)
Requires-Dist: pytest-qt
Requires-Dist: pytest-timeout
Requires-Dist: pigpio
